detect_layout.py
detect_text.py
ocr_app.py
ocr_text.py
run_ocr_app.py
surya/benchmark/bbox.py
surya/benchmark/metrics.py
surya/benchmark/tesseract.py
surya/benchmark/util.py
surya/detection.py
surya/input/langs.py
surya/input/load.py
surya/input/processing.py
surya/languages.py
surya/layout.py
surya/model/detection/segformer.py
surya/model/recognition/config.py
surya/model/recognition/decoder.py
surya/model/recognition/encoder.py
surya/model/recognition/model.py
surya/model/recognition/processor.py
surya/model/recognition/tokenizer.py
surya/ocr.py
surya/postprocessing/affinity.py
surya/postprocessing/fonts.py
surya/postprocessing/heatmap.py
surya/postprocessing/math/latex.py
surya/postprocessing/math/render.py
surya/postprocessing/text.py
surya/postprocessing/util.py
surya/recognition.py
surya/schema.py
surya/settings.py
surya_ocr_vlite-0.3.0.dist-info/LICENSE
surya_ocr_vlite-0.3.0.dist-info/METADATA
surya_ocr_vlite-0.3.0.dist-info/WHEEL
surya_ocr_vlite-0.3.0.dist-info/entry_points.txt
surya_ocr_vlite-0.3.0.dist-info/RECORD
