Metadata-Version: 2.1
Name: surya-ocr-vlite
Version: 0.3.0
Summary: OCR, layout analysis, and line detection in 90+ languages
Home-page: https://github.com/sdan/surya
License: GPL-3.0-or-later
Keywords: ocr,pdf,text detection,text recognition
Author: surya
Author-email: git@sdan.io
Requires-Python: >=3.9, !=2.7.*, !=3.0.*, !=3.1.*, !=3.2.*, !=3.3.*, !=3.4.*, !=3.5.*, !=3.6.*, !=3.7.*, !=3.8.*
Classifier: License :: OSI Approved :: GNU General Public License v3 or later (GPLv3+)
Classifier: Programming Language :: Python :: 3
Classifier: Programming Language :: Python :: 3.9
Classifier: Programming Language :: Python :: 3.10
Classifier: Programming Language :: Python :: 3.11
Requires-Dist: filetype (>=1.2.0,<2.0.0)
Requires-Dist: ftfy (>=6.1.3,<7.0.0)
Requires-Dist: opencv-python (>=4.9.0.80,<5.0.0.0)
Requires-Dist: pillow (>=10.2.0,<11.0.0)
Requires-Dist: pydantic (>=2.5.3,<3.0.0)
Requires-Dist: pydantic-settings (>=2.1.0,<3.0.0)
Requires-Dist: pypdfium2 (>=4.25.0,<5.0.0)
Requires-Dist: python-dotenv (>=1.0.0,<2.0.0)
Requires-Dist: tabulate (>=0.9.0,<0.10.0)
Requires-Dist: torch (>=2.1.2,<3.0.0)
Requires-Dist: transformers (==4.36.2)
Project-URL: Repository, https://github.com/sdan/surya
